[
    {
        "id": "61a3a054ea31d",
        "nickname": "DUPSKO SOCZYSTE",
        "points": 5000
    },
    {
        "id": "61a3a0573d0e6",
        "nickname": "DUPSKO SOCZYSTE",
        "points": 5000
    },
    {
        "id": "61a3a057cf3e2",
        "nickname": "DUPSKO SOCZYSTE",
        "points": 5000
    },
    {
        "id": "61a3a058039d8",
        "nickname": "DUPSKO SOCZYSTE",
        "points": 5000
    },
    {
        "id": "1",
        "nickname": "Player1",
        "points": 4000
    },
    {
        "id": "2",
        "nickname": "Player2",
        "points": 3800
    },
    {
        "id": "3",
        "nickname": "Player3",
        "points": 3400
    },
    {
        "id": "4",
        "nickname": "Player4",
        "points": 3200
    },
    {
        "id": "5",
        "nickname": "Player5",
        "points": 3000
    },
    {
        "id": "6",
        "nickname": "Player6",
        "points": 2750
    }
]